<?xml version="1.0" encoding="utf-8"?>
<!DOCTYPE hibernate-mapping PUBLIC "-//Hibernate/Hibernate Mapping DTD 3.0//EN"
"http://hibernate.sourceforge.net/hibernate-mapping-3.0.dtd">
<!-- 
    Mapping file autogenerated by MyEclipse Persistence Tools
-->
<hibernate-mapping>
    <class name="com.ascent.domain.Note" table="note" catalog="note">
        <id name="id" type="integer">
            <column name="id" />
            <generator class="native" />
        </id>
        <property name="title" type="string">
            <column name="title" length="45" not-null="true" />
        </property>
        <property name="content" type="string">
            <column name="content" length="65535" not-null="true" />
        </property>
        <property name="starttime" type="timestamp">
            <column name="starttime" length="19" not-null="true" />
        </property>
        <property name="endtime" type="timestamp">
            <column name="endtime" length="19" not-null="true" />
        </property>
        <property name="date" type="timestamp">
            <column name="date" length="19" not-null="true" />
        </property>
        <!-- <property name="state" type="string">
            <column name="state" length="45" not-null="true" />
        </property> -->
        <set name="plans" inverse="true" lazy="false" cascade="delete">
            <key>
                <column name="noteid" not-null="true" />
            </key>
            <one-to-many class="com.ascent.domain.Plan" />
        </set>
        <set name="notePublishers" inverse="false" table="note_publisher" lazy="false">
            <key>
                <column name="noteid" not-null="true" />
            </key>
            <many-to-many class="com.ascent.domain.User" column="publisherid"/>
        </set>
        <set name="noteExecutors" inverse="false" table="note_executor" lazy="false">
            <key>
                <column name="noteid" not-null="true" />
            </key>
            <many-to-many class="com.ascent.domain.User" column="executorid"/>
        </set>
        <set name="comments" inverse="true" cascade="delete">
            <key>
                <column name="noteid" not-null="true" />
            </key>
            <one-to-many class="com.ascent.domain.Comment" />
        </set>
        <many-to-one name="state" class="com.ascent.domain.State" fetch="select" lazy="false">
            <column name="stateid" not-null="true" />
        </many-to-one>         
        <many-to-one name="priority" class="com.ascent.domain.Priority" fetch="select" lazy="false">
            <column name="priorityid" not-null="true" />
        </many-to-one> 
        <many-to-one name="category" class="com.ascent.domain.Category" fetch="select" lazy="false">
            <column name="categoryid" not-null="true" />
        </many-to-one> 
    </class>
</hibernate-mapping>
